clickhouserag/config/__init__.py
clickhouserag/config/base_config.py
clickhouserag/config/clickhouse_config.py
clickhouserag/core/__init__.py
clickhouserag/data_access/__init__.py
clickhouserag/data_access/abstract_client.py
clickhouserag/data_access/abstract_table.py
clickhouserag/data_access/clickhouse_client.py
clickhouserag/data_access/clickhouse_table.py
clickhouserag/rag/__init__.py
clickhouserag/rag/base.py
clickhouserag/rag/manager.py
clickhouserag/utils/__init__.py
clickhouserag/vectorizers/__init__.py
clickhouserag/vectorizers/base.py
clickhouserag/vectorizers/manager.py
clickhouserag-0.2.0.dist-info/LICENSE
clickhouserag-0.2.0.dist-info/METADATA
clickhouserag-0.2.0.dist-info/WHEEL
clickhouserag-0.2.0.dist-info/RECORD
